grafana_gridder/__init__.py
grafana_gridder/grafana_gridder.py
grafana_gridder-0.1.0.dist-info/LICENSE
grafana_gridder-0.1.0.dist-info/METADATA
grafana_gridder-0.1.0.dist-info/WHEEL
grafana_gridder-0.1.0.dist-info/top_level.txt
grafana_gridder-0.1.0.dist-info/RECORD
