Metadata-Version: 2.1
Name: grafana_gridder
Version: 0.1.0
Summary: Create Grid layouts for Grafana dashboards.
Author-email: Eduard Dranca <ggridder@proton.me>
License: MIT License
Project-URL: Homepage, https://github.com/EduardDranca/GrafanaGridder
Project-URL: Issues, https://github.com/EduardDranca/GrafanaGridder/issues
Keywords: grafana,grid,dashboard
Classifier: License :: OSI Approved :: MIT License
Classifier: Programming Language :: Python
Classifier: Programming Language :: Python :: 3
Requires-Python: >=3.9
License-File: LICENSE
Requires-Dist: attr ==0.3.2
Requires-Dist: attrs ==23.2.0
Requires-Dist: grafanalib ==0.7.1
